[
  {
    "timestamp": "2026-03-24T06:44:02.877000+00:00",
    "channel_id": 1484027838708453386,
    "channel_name": "❄️┃lowlights",
    "author": "Horizon",
    "author_id": 1485178194284904448,
    "is_webhook": true,
    "webhook_id": 1485178194284904448,
    "message_id": 1485891930956234814,
    "content": "",
    "embeds": [
      {
        "title": "💵  $2.89M/s | Eid Eid Eid Sahur",
        "description": "```\n$2.89M/s | Eid Eid Eid Sahur\n```",
        "url": null,
        "type": "rich",
        "color": 4718721,
        "author": {
          "name": "🔔 Horizon Notifier",
          "url": null
        },
        "fields": [
          {
            "name": "🔗 Server Info",
            "value": "```\nID: f3fcb7ee-441e-4312-81c6-17fa989fd8af\nJoin: https://www.roblox.com/games/109983668079237?serverInstanceId=f3fcb7ee-441e-4312-81c6-17fa989fd8af\n```",
            "inline": false
          }
        ],
        "footer": {
          "text": "2026-03-24 02:44:02",
          "icon_url": null
        },
        "image": null,
        "thumbnail": "https://sabtradingvalues.com/images/items/Eid_Eid_Eid_Sahur.png"
      }
    ],
    "attachments": [],
    "stickers": []
  },
  {
    "timestamp": "2026-03-24T06:44:04.525000+00:00",
    "channel_id": 1484027838708453386,
    "channel_name": "❄️┃lowlights",
    "author": "Horizon",
    "author_id": 1485178194284904448,
    "is_webhook": true,
    "webhook_id": 1485178194284904448,
    "message_id": 1485891937868316793,
    "content": "",
    "embeds": [
      {
        "title": "💵  $4.35M/s | Chicleteirina Bicicleteirina",
        "description": "```\n$4.35M/s | Chicleteirina Bicicleteirina\n```",
        "url": null,
        "type": "rich",
        "color": 4718721,
        "author": {
          "name": "🔔 Horizon Notifier",
          "url": null
        },
        "fields": [
          {
            "name": "🔗 Server Info",
            "value": "```\nID: 6f3e04c7-a92f-4f4f-9a24-24263d34c439\nJoin: https://www.roblox.com/games/109983668079237?serverInstanceId=6f3e04c7-a92f-4f4f-9a24-24263d34c439\n```",
            "inline": false
          }
        ],
        "footer": {
          "text": "2026-03-24 02:44:04",
          "icon_url": null
        },
        "image": null,
        "thumbnail": "https://sabtradingvalues.com/images/items/Chicleteirina_Bicicleteirina.png"
      }
    ],
    "attachments": [],
    "stickers": []
  },
  {
    "timestamp": "2026-03-24T06:44:06.259000+00:00",
    "channel_id": 1484027838708453386,
    "channel_name": "❄️┃lowlights",
    "author": "Horizon",
    "author_id": 1485178194284904448,
    "is_webhook": true,
    "webhook_id": 1485178194284904448,
    "message_id": 1485891945141375006,
    "content": "",
    "embeds": [
      {
        "title": "💵  $5.26M/s | Noo my Candy",
        "description": "```\n$5.26M/s | Noo my Candy\n```",
        "url": null,
        "type": "rich",
        "color": 4718721,
        "author": {
          "name": "🔔 Horizon Notifier",
          "url": null
        },
        "fields": [
          {
            "name": "🔗 Server Info",
            "value": "```\nID: 0cb6485d-cd28-4c47-a903-8459dbefe07b\nJoin: https://www.roblox.com/games/109983668079237?serverInstanceId=0cb6485d-cd28-4c47-a903-8459dbefe07b\n```",
            "inline": false
          }
        ],
        "footer": {
          "text": "2026-03-24 02:44:06",
          "icon_url": null
        },
        "image": null,
        "thumbnail": "https://sabtradingvalues.com/images/items/Noo_my_Candy.png"
      }
    ],
    "attachments": [],
    "stickers": []
  },
  {
    "timestamp": "2026-03-24T06:44:06.690000+00:00",
    "channel_id": 1484027838708453386,
    "channel_name": "❄️┃lowlights",
    "author": "prestigiously",
    "author_id": 1244767123167776860,
    "is_webhook": false,
    "webhook_id": null,
    "message_id": 1485891946949116005,
    "content": "?purge 999",
    "embeds": [],
    "attachments": [],
    "stickers": []
  },
  {
    "timestamp": "2026-03-24T06:44:07.736000+00:00",
    "channel_id": 1484027838708453386,
    "channel_name": "❄️┃lowlights",
    "author": "Horizon",
    "author_id": 1485178194284904448,
    "is_webhook": true,
    "webhook_id": 1485178194284904448,
    "message_id": 1485891951336357889,
    "content": "",
    "embeds": [
      {
        "title": "💵  $5.82M/s | Serafinna Medusella",
        "description": "```\n$5.82M/s | Serafinna Medusella\n```",
        "url": null,
        "type": "rich",
        "color": 4718721,
        "author": {
          "name": "🔔 Horizon Notifier",
          "url": null
        },
        "fields": [
          {
            "name": "🔗 Server Info",
            "value": "```\nID: b56f62dd-6927-41f7-87de-0e7274276a0f\nJoin: https://www.roblox.com/games/109983668079237?serverInstanceId=b56f62dd-6927-41f7-87de-0e7274276a0f\n```",
            "inline": false
          }
        ],
        "footer": {
          "text": "2026-03-24 02:44:07",
          "icon_url": null
        },
        "image": null,
        "thumbnail": "https://sabtradingvalues.com/images/items/Serafinna_Medusella.png"
      }
    ],
    "attachments": [],
    "stickers": []
  },
  {
    "timestamp": "2026-03-24T06:44:11.262000+00:00",
    "channel_id": 1484027838708453386,
    "channel_name": "❄️┃lowlights",
    "author": "Horizon",
    "author_id": 1485178194284904448,
    "is_webhook": true,
    "webhook_id": 1485178194284904448,
    "message_id": 1485891966125215807,
    "content": "",
    "embeds": [
      {
        "title": "💵  $2.37M/s | 25",
        "description": "```\n$2.37M/s | 25\n```",
        "url": null,
        "type": "rich",
        "color": 4718721,
        "author": {
          "name": "🔔 Horizon Notifier",
          "url": null
        },
        "fields": [
          {
            "name": "🔗 Server Info",
            "value": "```\nID: 0794356b-06f2-49f0-b703-76c6db392dd2\nJoin: https://www.roblox.com/games/109983668079237?serverInstanceId=0794356b-06f2-49f0-b703-76c6db392dd2\n```",
            "inline": false
          }
        ],
        "footer": {
          "text": "2026-03-24 02:44:11",
          "icon_url": null
        },
        "image": null,
        "thumbnail": "https://sabtradingvalues.com/images/items/25.png"
      }
    ],
    "attachments": [],
    "stickers": []
  },
  {
    "timestamp": "2026-03-24T06:44:14.288000+00:00",
    "channel_id": 1484027838708453386,
    "channel_name": "❄️┃lowlights",
    "author": "Horizon",
    "author_id": 1485178194284904448,
    "is_webhook": true,
    "webhook_id": 1485178194284904448,
    "message_id": 1485891978817179678,
    "content": "",
    "embeds": [
      {
        "title": "💵  $2.32M/s | Telemorte",
        "description": "```\n$2.32M/s | Telemorte\n```",
        "url": null,
        "type": "rich",
        "color": 4718721,
        "author": {
          "name": "🔔 Horizon Notifier",
          "url": null
        },
        "fields": [
          {
            "name": "🔗 Server Info",
            "value": "```\nID: b56f62dd-6927-41f7-87de-0e7274276a0f\nJoin: https://www.roblox.com/games/109983668079237?serverInstanceId=b56f62dd-6927-41f7-87de-0e7274276a0f\n```",
            "inline": false
          }
        ],
        "footer": {
          "text": "2026-03-24 02:44:13",
          "icon_url": null
        },
        "image": null,
        "thumbnail": "https://sabtradingvalues.com/images/items/Telemorte.png"
      }
    ],
    "attachments": [],
    "stickers": []
  },
  {
    "timestamp": "2026-03-24T06:44:16.246000+00:00",
    "channel_id": 1484027838708453386,
    "channel_name": "❄️┃lowlights",
    "author": "Horizon",
    "author_id": 1485178194284904448,
    "is_webhook": true,
    "webhook_id": 1485178194284904448,
    "message_id": 1485891987029884989,
    "content": "",
    "embeds": [
      {
        "title": "💵  $1.29M/s | Cuadramat and Pakrahmatmamat",
        "description": "```\n$1.29M/s | Cuadramat and Pakrahmatmamat\n```",
        "url": null,
        "type": "rich",
        "color": 4718721,
        "author": {
          "name": "🔔 Horizon Notifier",
          "url": null
        },
        "fields": [
          {
            "name": "🔗 Server Info",
            "value": "```\nID: bc4c0541-921e-4189-b7d3-9b56826a5a1c\nJoin: https://www.roblox.com/games/109983668079237?serverInstanceId=bc4c0541-921e-4189-b7d3-9b56826a5a1c\n```",
            "inline": false
          }
        ],
        "footer": {
          "text": "2026-03-24 02:44:16",
          "icon_url": null
        },
        "image": null,
        "thumbnail": "https://sabtradingvalues.com/images/items/Cuadramat_and_Pakrahmatmamat.png"
      }
    ],
    "attachments": [],
    "stickers": []
  },
  {
    "timestamp": "2026-03-24T06:44:17.869000+00:00",
    "channel_id": 1484027838708453386,
    "channel_name": "❄️┃lowlights",
    "author": "Horizon",
    "author_id": 1485178194284904448,
    "is_webhook": true,
    "webhook_id": 1485178194284904448,
    "message_id": 1485891993837244428,
    "content": "",
    "embeds": [
      {
        "title": "💵  $1.32M/s | Cuadramat and Pakrahmatmamat",
        "description": "```\n$1.32M/s | Cuadramat and Pakrahmatmamat\n```",
        "url": null,
        "type": "rich",
        "color": 4718721,
        "author": {
          "name": "🔔 Horizon Notifier",
          "url": null
        },
        "fields": [
          {
            "name": "🔗 Server Info",
            "value": "```\nID: 536d8f28-56b5-4ac6-b311-297cbee72777\nJoin: https://www.roblox.com/games/109983668079237?serverInstanceId=536d8f28-56b5-4ac6-b311-297cbee72777\n```",
            "inline": false
          }
        ],
        "footer": {
          "text": "2026-03-24 02:44:17",
          "icon_url": null
        },
        "image": null,
        "thumbnail": "https://sabtradingvalues.com/images/items/Cuadramat_and_Pakrahmatmamat.png"
      }
    ],
    "attachments": [],
    "stickers": []
  }
]